drag/__init__.py
drag/utils.py
drag/base/__init__.py
drag/base/base.py
drag/chroma_db/__init__.py
drag/chroma_db/chroma.py
drag/commands/drag_clean.py
drag/groq/__init__.py
drag/groq/groq_chat.py
drag/openai/__init__.py
drag/openai/openai_chat.py
drag/qdrant_db/qdrant.py
drag_copilot-0.0.1.dist-info/LICENSE
drag_copilot-0.0.1.dist-info/METADATA
drag_copilot-0.0.1.dist-info/WHEEL
drag_copilot-0.0.1.dist-info/top_level.txt
drag_copilot-0.0.1.dist-info/RECORD
